dedust/__init__.py
dedust/constants.py
dedust/contracts/__init__.py
dedust/contracts/dex/__init__.py
dedust/contracts/dex/common/__init__.py
dedust/contracts/dex/common/asset.py
dedust/contracts/dex/common/asset_error.py
dedust/contracts/dex/common/asset_type.py
dedust/contracts/dex/common/readiness_status.py
dedust/contracts/dex/factory/__init__.py
dedust/contracts/dex/factory/factory.py
dedust/contracts/dex/liquidity_deposit/__init__.py
dedust/contracts/dex/liquidity_deposit/liquidity_deposit.py
dedust/contracts/dex/pool/__init__.py
dedust/contracts/dex/pool/pool.py
dedust/contracts/dex/pool/pool_type.py
dedust/contracts/dex/vault/__init__.py
dedust/contracts/dex/vault/vault.py
dedust/contracts/dex/vault/vault_jetton.py
dedust/contracts/dex/vault/vault_native.py
dedust/contracts/jettons/__init__.py
dedust/contracts/jettons/jetton_root.py
dedust/contracts/jettons/jetton_wallet.py
dedust-1.1.3.dist-info/LICENSE.md
dedust-1.1.3.dist-info/WHEEL
dedust-1.1.3.dist-info/METADATA
dedust-1.1.3.dist-info/RECORD
