Metadata-Version: 2.1
Name: dedust
Version: 1.1.3
Summary: DeDust - DeDust SDK for Python.
Author: Shibdev, Dalvpv
Requires-Dist: httpx==0.19.0
Requires-Dist: pytoniq>=0.1.19
